kdr_utils/__init__.py
kdr_utils/kdr_utils.py
kdr_utils-1.0.4.dist-info/METADATA
kdr_utils-1.0.4.dist-info/WHEEL
kdr_utils-1.0.4.dist-info/top_level.txt
kdr_utils-1.0.4.dist-info/RECORD
