Metadata-Version: 2.4
Name: kdr_utils
Version: 1.0.4
Summary: Helpful stuff
Author-email: Shakieran <shaciaran@xiyr.xyz>
License-Expression: MIT
Requires-Python: >=3.10
Requires-Dist: pyserial>=3.5
